{
  "articles": [
    {
      "id": 1,
      "title": "this is the first ever post",
      "body": "this is the first ever posts body",
      "likes": 0,
      "comments": [
        {
          "text": "this is the comment text",
          "giphyUrl": "this is the giphy url."
        }
      ]
    },
    {
      "id": "2adfgsdfg-wyr5hsthre-aehsrthadrfg-athsrthsh",
      "title": "second article title",
      "body": "this is the body",
      "likes": 9,
      "comments": [
        {
          "text": "this is the comment",
          "giphyUrl": "url.com"
        }
      ]
    },
    {
      "id": "398d5832-bfc2-4fdd-88ed-b1a65fb022e8",
      "body": "dfdsfdfcdsdscf",
      "likes": 0,
      "comments": [
        {
          "text": "",
          "giphyUrl": ""
        }
      ]
    },
    {
      "id": "e142e5bc-1dea-4493-9a37-cbc2943d5900",
      "body": "fdfvfdd",
      "likes": 0,
      "comments": [
        {
          "text": "",
          "giphyUrl": ""
        }
      ]
    },
    {
      "id": "34c02770-382c-476e-95b5-9c9c72ca9804",
      "body": "sfddcsdcdscsd",
      "likes": 0,
      "comments": [
        {
          "text": "",
          "giphyUrl": ""
        }
      ]
    },
    {
      "id": "bfcceb07-6c68-4f44-b162-f40d5a141428",
      "title": "here it goes",
      "body": "i tried my best ",
      "likes": 0,
      "comments": [
        {
          "text": "",
          "giphyUrl": ""
        }
      ]
    },
    {
      "id": "a7a0a3b6-34c1-406b-9871-d2875d865ead",
      "title": "anonymates",
      "body": "anonymates hard working ",
      "likes": 0,
      "comments": [
        {
          "text": "",
          "giphyUrl": ""
        }
      ]
    },
    {
      "id": "2881418f-90cc-4b57-8746-ed3f3ebbd629",
      "title": "202222222222",
      "body": "2022 2022",
      "likes": 0,
      "comments": [
        {
          "text": "",
          "giphyUrl": ""
        }
      ]
    },
    {
      "id": "fa69e39c-2a2c-4b71-9d43-e457994ca0ad",
      "title": "2023",
      "body": "ghggkfk;fx;lfknfd;fgdgff",
      "likes": 0,
      "comments": [
        {
          "text": "",
          "giphyUrl": ""
        }
      ]
    },
    {
      "id": "11aa733e-934b-45d7-8d05-933c8344c4af",
      "title": "ghfhfghgfhfgffgh",
      "body": "ghghhhgfh",
      "likes": 0,
      "comments": [
        {
          "text": "",
          "giphyUrl": ""
        }
      ]
    },
    {
      "id": "dbc32ca0-6014-4fee-b9d0-1de11b7fd122",
      "title": "dsddsssssssssss",
      "body": "momomomommom",
      "likes": 0,
      "comments": [
        {
          "text": "",
          "giphyUrl": ""
        }
      ]
    },
    {
      "id": "a2f40064-87b1-4b56-acc5-3a7148d28c01",
      "title": "jjjjjjjjj",
      "body": "jjjjjjjjjjj",
      "likes": 0,
      "comments": [
        {
          "text": "",
          "giphyUrl": ""
        }
      ]
    },
    {
      "id": "358efd51-cc65-4792-b160-58260c5ee8bc",
      "title": "aaaaaaaaa",
      "body": "aaaaaaaaa",
      "likes": 0,
      "comments": [
        {
          "text": "",
          "giphyUrl": ""
        }
      ]
    },
    {
      "id": "9cbf2296-3bac-482a-ad63-a1d15461e016",
      "title": "bbbbbbbbbb",
      "body": "bbbbbbbbbbb",
      "likes": 0,
      "comments": [
        {
          "text": "",
          "giphyUrl": ""
        }
      ]
    },
    {
      "id": "a73b08a7-c066-4903-8198-cd6d6a9a04d0",
      "title": "fvfddvfddfvfd",
      "body": "fdgdgvfdgfdvfdv",
      "likes": 0,
      "comments": [
        {
          "text": "",
          "giphyUrl": ""
        }
      ]
    },
    {
      "id": "31490414-0f4d-4517-9067-240ced411f0f",
      "title": "nbvnvbnvnvbnbnvb",
      "body": "hgfynghvnvbnbvbn",
      "likes": 0,
      "comments": [
        {
          "text": "",
          "giphyUrl": ""
        }
      ]
    },
    {
      "id": "49a44c96-fc45-43bc-9ba5-934d52e560d7",
      "title": "vnbbvnnvnvbb",
      "body": "bvnvnvbn",
      "likes": 0,
      "comments": [
        {
          "text": "",
          "giphyUrl": ""
        }
      ]
    },
    {
      "id": "e404f8ce-a689-4928-ab43-f5c454381e42",
      "title": "gfngnbvnvb",
      "body": "jhghjhghjngnh",
      "likes": 0,
      "comments": [
        {
          "text": "",
          "giphyUrl": ""
        }
      ]
    },
    {
      "id": "7cb8b2a7-0da4-4328-9e40-e9a6ba12ef10",
      "title": "vcvcxvc",
      "body": "vvvcxxvc",
      "likes": 0,
      "comments": [
        {
          "text": "",
          "giphyUrl": ""
        }
      ]
    },
    {
      "id": "bcfee67f-8f97-4f5f-8e67-dc6f9ff5f6c7",
      "title": "tuesday",
      "body": "tuesday",
      "likes": 0,
      "comments": [
        {
          "text": "",
          "giphyUrl": ""
        }
      ]
    },
    {
      "id": "4ff958a1-3e4e-405a-9f04-c594eff09db1",
      "title": "wednesday",
      "body": "wednesday",
      "likes": 0,
      "comments": [
        {
          "text": "",
          "giphyUrl": ""
        }
      ]
    },
    {
      "id": "fe13de7a-e5a6-4c5d-b4f6-612021803f46",
      "title": "thursday",
      "body": "fdsfdsfdsfsdfsdfsdfsdfsdf",
      "likes": 0,
      "comments": [
        {
          "text": "",
          "giphyUrl": ""
        }
      ]
    },
    {
      "id": "5666ddf9-70ad-4da2-8e20-c0683dd17743",
      "title": "jjjjjj",
      "body": "jhjjjjjjjj",
      "likes": 0,
      "comments": [
        {
          "text": "",
          "giphyUrl": ""
        }
      ]
    },
    {
      "id": "4d80c6a7-7093-43c0-a165-3eba4dea01b5",
      "title": "ggggggggg",
      "body": "ggggggeeeeeeee",
      "likes": 0,
      "comments": [
        {
          "text": "",
          "giphyUrl": ""
        }
      ]
    },
    {
      "id": "7bec6bca-0ac5-47c2-addc-33193ae2fa8a",
      "title": "zzzzzzzz",
      "body": "zzzzzz",
      "likes": 0,
      "comments": [
        {
          "text": "",
          "giphyUrl": ""
        }
      ]
    },
    {
      "id": "e32785ed-5225-447d-920f-390581d792c4",
      "title": "aaaaaaaaaaaaaaa",
      "body": "aaaaaaaaaaaaaaaaaaaaaaaa",
      "likes": 0,
      "comments": [
        {
          "text": "",
          "giphyUrl": ""
        }
      ]
    }
  ]
}